hero_img_categories/__init__.py
hero_img_categories/frontend/build/asset-manifest.json
hero_img_categories/frontend/build/bootstrap.min.css
hero_img_categories/frontend/build/bootstrap.min.css.map
hero_img_categories/frontend/build/index.html
hero_img_categories/frontend/build/static/css/main.6da88529.css
hero_img_categories/frontend/build/static/css/main.6da88529.css.map
hero_img_categories/frontend/build/static/js/main.80772349.js
hero_img_categories/frontend/build/static/js/main.80772349.js.LICENSE.txt
hero_img_categories/frontend/build/static/js/main.80772349.js.map
image_component_streamlit-0.0.8.dist-info/LICENSE
image_component_streamlit-0.0.8.dist-info/METADATA
image_component_streamlit-0.0.8.dist-info/WHEEL
image_component_streamlit-0.0.8.dist-info/top_level.txt
image_component_streamlit-0.0.8.dist-info/RECORD
